aidolon_browser_client/__init__.py
aidolon_browser_client/api/__init__.py
aidolon_browser_client/api/browser_actions/__init__.py
aidolon_browser_client/api/browser_actions/click_element.py
aidolon_browser_client/api/browser_actions/drag_and_drop.py
aidolon_browser_client/api/browser_actions/navigate_browser.py
aidolon_browser_client/api/browser_actions/press_key.py
aidolon_browser_client/api/browser_actions/type_text.py
aidolon_browser_client/api/content_extraction/__init__.py
aidolon_browser_client/api/content_extraction/generate_pdf.py
aidolon_browser_client/api/content_extraction/scrape_information.py
aidolon_browser_client/api/content_extraction/scrape_page.py
aidolon_browser_client/api/content_extraction/take_screenshot.py
aidolon_browser_client/api/session_management/__init__.py
aidolon_browser_client/api/session_management/close_all_browser_sessions.py
aidolon_browser_client/api/session_management/close_browser_session.py
aidolon_browser_client/api/session_management/create_browser_session.py
aidolon_browser_client/api/session_management/get_browser_context.py
aidolon_browser_client/api/session_management/get_session_status.py
aidolon_browser_client/api/session_management/list_browser_sessions.py
aidolon_browser_client/api/session_management/update_session_timeout.py
aidolon_browser_client/browser/__init__.py
aidolon_browser_client/browser/browser_session.py
aidolon_browser_client/client.py
aidolon_browser_client/errors.py
aidolon_browser_client/models/__init__.py
aidolon_browser_client/models/browser_context.py
aidolon_browser_client/models/browser_context_cookies_item.py
aidolon_browser_client/models/browser_context_local_storage.py
aidolon_browser_client/models/browser_context_session_storage.py
aidolon_browser_client/models/browser_session.py
aidolon_browser_client/models/browser_session_live_session_type_0.py
aidolon_browser_client/models/browser_session_live_session_type_0_viewport.py
aidolon_browser_client/models/browser_session_status.py
aidolon_browser_client-1.0.1.dist-info/LICENSE
aidolon_browser_client-1.0.1.dist-info/METADATA
aidolon_browser_client-1.0.1.dist-info/WHEEL
aidolon_browser_client-1.0.1.dist-info/RECORD
