Metadata-Version: 2.3
Name: aidolon-browser-client
Version: 1.0.1
Summary: A client library for accessing Aidolon Browser
License: MIT
Author: Aidolon Systems
Requires-Python: >=3.9,<4.0
Classifier: Intended Audience :: Developers
Classifier: License :: OSI Approved :: MIT License
Classifier: Operating System :: OS Independent
Classifier: Programming Language :: Python :: 3
Classifier: Programming Language :: Python :: 3.9
Classifier: Programming Language :: Python :: 3.10
Classifier: Programming Language :: Python :: 3.11
Classifier: Programming Language :: Python :: 3.12
Classifier: Programming Language :: Python :: 3.13
Classifier: Topic :: Internet :: WWW/HTTP :: Browsers
Requires-Dist: attrs (>=22.2.0)
Requires-Dist: httpx (>=0.20.0,<0.29.0)
Requires-Dist: python-dateutil (>=2.8.0,<3.0.0)
Project-URL: Homepage, https://github.com/AidolonSystems/aidolon-browser-client
Project-URL: Repository, https://github.com/AidolonSystems/aidolon-browser-client
